hydrodata/__init__.py
hydrodata/exceptions.py
hydrodata/helpers.py
hydrodata/hydrodata.py
hydrodata/plot.py
hydrodata/print_versions.py
hydrodata-0.9.1.dist-info/AUTHORS.rst
hydrodata-0.9.1.dist-info/LICENSE
hydrodata-0.9.1.dist-info/METADATA
hydrodata-0.9.1.dist-info/WHEEL
hydrodata-0.9.1.dist-info/top_level.txt
hydrodata-0.9.1.dist-info/RECORD
