Metadata-Version: 2.1
Name: hydrodata
Version: 0.9.1
Summary: A portal to access hydrology and climatology databases in Python
Home-page: https://github.com/cheginit/hydrodata
Author: Taher Chegini
Author-email: cheginit@gmail.com
License: MIT license
Platform: UNKNOWN
Classifier: Development Status :: 3 - Alpha
Classifier: License :: OSI Approved :: MIT License
Classifier: Operating System :: OS Independent
Classifier: Intended Audience :: Science/Research
Classifier: Programming Language :: Python
Classifier: Programming Language :: Python :: 3
Classifier: Programming Language :: Python :: 3.6
Classifier: Programming Language :: Python :: 3.7
Classifier: Programming Language :: Python :: 3.8
Classifier: Topic :: Scientific/Engineering
Requires-Python: >=3.6
Requires-Dist: aiodns
Requires-Dist: aiohttp
Requires-Dist: brotlipy
Requires-Dist: chardet
Requires-Dist: dask
Requires-Dist: defusedxml
Requires-Dist: folium
Requires-Dist: geopandas
Requires-Dist: lxml
Requires-Dist: matplotlib
Requires-Dist: nest-asyncio
Requires-Dist: netCDF4
Requires-Dist: networkx
Requires-Dist: orjson
Requires-Dist: owslib
Requires-Dist: py3dep
Requires-Dist: pyarrow
Requires-Dist: pydaymet
Requires-Dist: pygeoogc
Requires-Dist: pygeoutils
Requires-Dist: pynhd
Requires-Dist: pyproj
Requires-Dist: rasterio
Requires-Dist: requests
Requires-Dist: setuptools
Requires-Dist: shapely
Requires-Dist: simplejson
Requires-Dist: xarray
